cesm.py
core/__init__.py
core/data_access.py
core/input_parser.py
core/model.py
core/params.py
core/plotter.py
cesm-0.0.9.dist-info/LICENSE.md
cesm-0.0.9.dist-info/METADATA
cesm-0.0.9.dist-info/WHEEL
cesm-0.0.9.dist-info/entry_points.txt
cesm-0.0.9.dist-info/top_level.txt
cesm-0.0.9.dist-info/RECORD
